ec2_clone/__init__.py
ec2_clone/__main__.py
ec2_clone/args.py
ec2_clone/aws.py
ec2_clone/cli.py
ec2_clone/clone.py
ec2_clone/hibernate.py
ec2_clone/relaunch.py
ec2_clone/rollback.py
ec2_clone/settings.py
ec2_clone/util/__init__.py
ec2_clone/util/ami.py
ec2_clone/util/eip.py
ec2_clone/util/instance.py
ec2_clone/util/log.py
ec2_clone/util/vpc.py
ec2_clone-1.1.0.dist-info/METADATA
ec2_clone-1.1.0.dist-info/WHEEL
ec2_clone-1.1.0.dist-info/entry_points.txt
ec2_clone-1.1.0.dist-info/top_level.txt
ec2_clone-1.1.0.dist-info/RECORD
