Metadata-Version: 2.1
Name: ec2-clone
Version: 1.1.0
Summary: Relaunch an AWS instance whilst maintaining the same configuration and data
Author: Joaquim Gomez
Requires-Python: >=3.6, <4
Requires-Dist: click
Requires-Dist: boto3
Requires-Dist: colorama
